tapioca_teamculture/__init__.py
tapioca_teamculture/resource_mapping.py
tapioca_teamculture/tapioca_teamculture.py
tapioca_teamculture-0.2.0.dist-info/LICENSE
tapioca_teamculture-0.2.0.dist-info/WHEEL
tapioca_teamculture-0.2.0.dist-info/METADATA
tapioca_teamculture-0.2.0.dist-info/RECORD
