Metadata-Version: 2.1
Name: tapioca-teamculture
Version: 0.2.0
Summary: TeamCulture API wrapper using tapioca
Author: Felipe Guilherme Sabino
Author-email: felipe@sabino.pro
Requires-Python: >=3.7,<4.0
Classifier: Programming Language :: Python :: 3
Classifier: Programming Language :: Python :: 3.10
Classifier: Programming Language :: Python :: 3.7
Classifier: Programming Language :: Python :: 3.8
Classifier: Programming Language :: Python :: 3.9
Requires-Dist: tapioca-wrapper (>=2.1.0,<3.0.0)
